imapy_music/__init__.py
imapy_music/scripts/__init__.py
imapy_music/scripts/meter_collection.py
imapy_music/scripts/metro_math.py
imapy_music/scripts/metro_weights_mazzola.py
imapy_music/scripts/metrum.py
imapy_music/scripts/onset_group_memory.py
imapy_music/scripts/weight_set.py
IMAPY_music-0.1.6a0.dist-info/LICENSE
IMAPY_music-0.1.6a0.dist-info/METADATA
IMAPY_music-0.1.6a0.dist-info/WHEEL
IMAPY_music-0.1.6a0.dist-info/top_level.txt
IMAPY_music-0.1.6a0.dist-info/RECORD
