Metadata-Version: 2.1
Name: IMAPY-music
Version: 0.1.6a0
Summary: UNKNOWN
Home-page: https://github.com/NadiaCarvalho/IMAPY-music
Author: Nádia Carvalho
Author-email: nadiacarvalho118@gmail.com
License: GNU Lesser General Public License v3.0
Platform: UNKNOWN
License-File: LICENSE
